{"trial_id": "393ebb2aa6a7b4071f7fc30c2b853922", "hyperparameters": {"space": [{"class_name": "Choice", "config": {"name": "n_layers", "default": 3, "conditions": [], "values": [3, 4], "ordered": true}}, {"class_name": "Choice", "config": {"name": "first_layer_nodes", "default": 500, "conditions": [], "values": [500, 300], "ordered": true}}, {"class_name": "Choice", "config": {"name": "last_layer_nodes", "default": 100, "conditions": [], "values": [100, 50], "ordered": true}}, {"class_name": "Choice", "config": {"name": "learning_rate", "default": 0.1, "conditions": [], "values": [0.1, 0.01, 0.001], "ordered": true}}, {"class_name": "Choice", "config": {"name": "activation", "default": "relu", "conditions": [], "values": ["relu", "sigmoid"], "ordered": false}}], "values": {"n_layers": 4, "first_layer_nodes": 300, "last_layer_nodes": 50, "learning_rate": 0.001, "activation": "relu"}}, "metrics": {"metrics": {"loss": {"direction": "min", "observations": [{"value": [2.988478660583496], "step": 0}]}, "accuracy": {"direction": "max", "observations": [{"value": [0.10122666507959366], "step": 0}]}, "val_loss": {"direction": "min", "observations": [{"value": [2.316958427429199], "step": 0}]}, "val_accuracy": {"direction": "max", "observations": [{"value": [0.09960000216960907], "step": 0}]}}}, "score": 0.09960000216960907, "best_step": 0, "status": "COMPLETED"}